colorprintx/__init__.py
colorprintx/printer.py
rahulsahni_colorprintx-0.1.0.dist-info/METADATA
rahulsahni_colorprintx-0.1.0.dist-info/WHEEL
rahulsahni_colorprintx-0.1.0.dist-info/top_level.txt
rahulsahni_colorprintx-0.1.0.dist-info/RECORD
