Metadata-Version: 2.4
Name: rahulsahni-colorprintx
Version: 0.1.0
Summary: Simple colored print utility for Python
Author: Rahul Sahni
License: MIT
Requires-Python: >=3.8
